spotify_alarm/__init__.py
spotify_alarm/alarm_clock.py
spotify_alarm-0.1.0.dist-info/LICENSE
spotify_alarm-0.1.0.dist-info/METADATA
spotify_alarm-0.1.0.dist-info/WHEEL
spotify_alarm-0.1.0.dist-info/entry_points.txt
spotify_alarm-0.1.0.dist-info/top_level.txt
spotify_alarm-0.1.0.dist-info/RECORD
